CONTRIBUTING.rst
LICENSE
MANIFEST.in
README.rst
requirements.txt
setup.cfg
setup.py
django_filtrate.egg-info/PKG-INFO
django_filtrate.egg-info/SOURCES.txt
django_filtrate.egg-info/dependency_links.txt
django_filtrate.egg-info/not-zip-safe
django_filtrate.egg-info/requires.txt
django_filtrate.egg-info/top_level.txt
filtrate/__init__.py
filtrate/admin.py
filtrate/apps.py
filtrate/filters.py
filtrate/mixins.py
filtrate/models.py
filtrate/registry.py
filtrate/settings.py
filtrate/migrations/0001_initial.py
filtrate/migrations/__init__.py