Metadata-Version: 1.1
Name: django-filtrate
Version: 0.1.1
Summary: Customizable Django Admin filters
Home-page: https://github.com/Lenders-Cooperative/django-filtrate
Author: Lenders-Cooperative
Author-email: dgraves@thesummitgrp.com
License: BSD
Keywords: django-filtrate
Platform: UNKNOWN
Classifier: Development Status :: 3 - Alpha
Classifier: Framework :: Django :: 3.0
Classifier: Framework :: Django :: 3.1
Classifier: Framework :: Django :: 3.2
Classifier: Framework :: Django :: 4.0
Classifier: Framework :: Django :: 4.1
Classifier: Intended Audience :: Developers
Classifier: License :: OSI Approved :: BSD License
Classifier: Natural Language :: English
Classifier: Programming Language :: Python :: 3
Classifier: Programming Language :: Python :: 3.8
Classifier: Programming Language :: Python :: 3.9
Classifier: Programming Language :: Python :: 3.10
